wagtail_surveyjs-0.3.0.dist-info/licenses/LICENSE
wagtailsurveyjs/__init__.py
wagtailsurveyjs/admin.py
wagtailsurveyjs/apps.py
wagtailsurveyjs/forms.py
wagtailsurveyjs/models.py
wagtailsurveyjs/serializers.py
wagtailsurveyjs/tests.py
wagtailsurveyjs/urls.py
wagtailsurveyjs/views.py
wagtailsurveyjs/wagtail_hooks.py
wagtailsurveyjs/migrations/0001_initial.py
wagtailsurveyjs/migrations/__init__.py
wagtailsurveyjs/static/wagtailsurveyjs/css/creator.css
wagtailsurveyjs/static/wagtailsurveyjs/css/dashboard.css
wagtailsurveyjs/static/wagtailsurveyjs/css/vendor/defaultV2.min.css
wagtailsurveyjs/static/wagtailsurveyjs/js/creator.js
wagtailsurveyjs/static/wagtailsurveyjs/js/creator.js.LICENSE.txt
wagtailsurveyjs/static/wagtailsurveyjs/js/dashboard.js
wagtailsurveyjs/static/wagtailsurveyjs/js/dashboard.js.LICENSE.txt
wagtailsurveyjs/static/wagtailsurveyjs/js/vendor/jquery.min.js
wagtailsurveyjs/static/wagtailsurveyjs/js/vendor/survey.jquery.js
wagtailsurveyjs/templates/wagtailsurveyjs/admin_survey_creator.html
wagtailsurveyjs/templates/wagtailsurveyjs/admin_survey_results.html
wagtailsurveyjs/templates/wagtailsurveyjs/survey_form_page_js_include.html
wagtail_surveyjs-0.3.0.dist-info/METADATA
wagtail_surveyjs-0.3.0.dist-info/WHEEL
wagtail_surveyjs-0.3.0.dist-info/top_level.txt
wagtail_surveyjs-0.3.0.dist-info/RECORD
