Metadata-Version: 2.4
Name: wagtail-surveyjs
Version: 0.3.0
Summary: Integrate SurveyJS in Wagtail Projects.
Home-page: https://github.com/wmo-raf/wagtail-surveyjs
Author: Erick Otenyo
Author-email: otenyo.erick@gmail.com
License: MIT
Classifier: Development Status :: 4 - Beta
Classifier: Environment :: Web Environment
Classifier: Intended Audience :: Developers
Classifier: License :: OSI Approved :: MIT License
Classifier: Operating System :: OS Independent
Classifier: Programming Language :: Python :: 3 :: Only
Classifier: Programming Language :: Python :: 3.9
Classifier: Programming Language :: Python :: Implementation :: CPython
Classifier: Topic :: Software Development :: Libraries :: Application Frameworks
Classifier: Topic :: Software Development :: Libraries :: Python Modules
Requires-Python: >=3.9
License-File: LICENSE
Requires-Dist: wagtail>=7.0
Requires-Dist: wagtail-modeladmin>=2.0.0
Dynamic: license-file
